{"canvas":{},"ctx":{},"isActive":false,"mouseDownPoint":{"x":676,"y":453},"mouseUpPoint":{"x":678,"y":685},"gravity":{"x":0,"y":0.1},"springs":[{"a":{"position":{"x":453,"y":453},"velocity":{"x":0,"y":0},"index":0,"highlight":[20,23,172]},"b":{"position":{"x":517,"y":229},"velocity":{"x":0,"y":0},"index":1,"highlight":[218,125,217]},"k":0.1,"restLength":232.96351645697658,"broken":false,"index":0},{"a":{"position":{"x":517,"y":229},"velocity":{"x":0,"y":0},"index":1,"highlight":[218,125,217]},"b":{"position":{"x":562,"y":453},"velocity":{"x":0,"y":0},"index":2,"highlight":[148,102,101]},"k":0.1,"restLength":228.47538160598398,"broken":false,"index":1},{"a":{"position":{"x":562,"y":453},"velocity":{"x":0,"y":0},"index":2,"highlight":[148,102,101]},"b":{"position":{"x":610,"y":228},"velocity":{"x":0,"y":0},"index":3,"highlight":[105,250,219]},"k":0.1,"restLength":230.0630348404541,"broken":false,"index":2},{"a":{"position":{"x":610,"y":228},"velocity":{"x":0,"y":0},"index":3,"highlight":[105,250,219]},"b":{"position":{"x":678,"y":453},"velocity":{"x":0,"y":0},"index":4,"highlight":[115,181,102]},"k":0.1,"restLength":235.0510582830888,"broken":false,"index":3},{"a":{"position":{"x":678,"y":453},"velocity":{"x":0,"y":0},"index":4,"highlight":[115,181,102]},"b":{"position":{"x":748,"y":229},"velocity":{"x":0,"y":0},"index":5,"highlight":[52,201,147]},"k":0.1,"restLength":234.68276459936294,"broken":false,"index":4},{"a":{"position":{"x":748,"y":229},"velocity":{"x":0,"y":0},"index":5,"highlight":[52,201,147]},"b":{"position":{"x":787,"y":453},"velocity":{"x":0,"y":0},"index":6,"highlight":[182,60,103]},"k":0.1,"restLength":227.36974292988063,"broken":false,"index":5},{"a":{"position":{"x":787,"y":453},"velocity":{"x":0,"y":0},"index":6,"highlight":[182,60,103]},"b":{"position":{"x":834,"y":231},"velocity":{"x":0,"y":0},"index":7,"highlight":[188,193,184]},"k":0.1,"restLength":226.92069099136816,"broken":false,"index":6},{"a":{"position":{"x":834,"y":231},"velocity":{"x":0,"y":0},"index":7,"highlight":[188,193,184]},"b":{"position":{"x":901,"y":451},"velocity":{"x":0,"y":0},"index":8,"highlight":[46,76,141]},"k":0.1,"restLength":229.97608571327584,"broken":false,"index":7},{"a":{"position":{"x":901,"y":451},"velocity":{"x":0,"y":0},"index":8,"highlight":[46,76,141]},"b":{"position":{"x":979,"y":229},"velocity":{"x":0,"y":0},"index":9,"highlight":[156,11,178]},"k":0.1,"restLength":235.30405861353094,"broken":false,"index":8},{"a":{"position":{"x":979,"y":229},"velocity":{"x":0,"y":0},"index":9,"highlight":[156,11,178]},"b":{"position":{"x":1015,"y":454},"velocity":{"x":0,"y":0},"index":10,"highlight":[125,139,108]},"k":0.1,"restLength":227.86180022109892,"broken":false,"index":9},{"a":{"position":{"x":1015,"y":454},"velocity":{"x":0,"y":0},"index":10,"highlight":[125,139,108]},"b":{"position":{"x":1045,"y":228},"velocity":{"x":0,"y":0},"index":11,"highlight":[216,39,115]},"k":0.1,"restLength":227.98245546532743,"broken":false,"index":10},{"a":{"position":{"x":1045,"y":228},"velocity":{"x":0,"y":0},"index":11,"highlight":[216,39,115]},"b":{"position":{"x":1132,"y":454},"velocity":{"x":0,"y":0},"index":12,"highlight":[244,194,4]},"k":0.1,"restLength":242.1672975444868,"broken":false,"index":11},{"a":{"position":{"x":1132,"y":454},"velocity":{"x":0,"y":0},"index":12,"highlight":[244,194,4]},"b":{"position":{"x":1131,"y":679},"velocity":{"x":0,"y":0},"index":13,"highlight":[40,65,214]},"k":0.1,"restLength":225.00222221124838,"broken":false,"index":12},{"a":{"position":{"x":1131,"y":679},"velocity":{"x":0,"y":0},"index":13,"highlight":[40,65,214]},"b":{"position":{"x":904,"y":906},"velocity":{"x":0,"y":0},"index":14,"highlight":[52,157,14]},"k":0.1,"restLength":321.02647865869255,"broken":false,"index":13},{"a":{"position":{"x":904,"y":906},"velocity":{"x":0,"y":0},"index":14,"highlight":[52,157,14]},"b":{"position":{"x":679,"y":906},"velocity":{"x":0,"y":0},"index":15,"highlight":[226,86,82]},"k":0.1,"restLength":225,"broken":false,"index":14},{"a":{"position":{"x":679,"y":906},"velocity":{"x":0,"y":0},"index":15,"highlight":[226,86,82]},"b":{"position":{"x":453,"y":679},"velocity":{"x":0,"y":0},"index":16,"highlight":[230,117,173]},"k":0.1,"restLength":320.3201523476161,"broken":false,"index":15},{"a":{"position":{"x":453,"y":679},"velocity":{"x":0,"y":0},"index":16,"highlight":[230,117,173]},"b":{"position":{"x":453,"y":453},"velocity":{"x":0,"y":0},"index":0,"highlight":[20,23,172]},"k":0.1,"restLength":226,"broken":false,"index":16},{"a":{"position":{"x":453,"y":453},"velocity":{"x":0,"y":0},"index":0,"highlight":[20,23,172]},"b":{"position":{"x":562,"y":453},"velocity":{"x":0,"y":0},"index":2,"highlight":[148,102,101]},"k":0.1,"restLength":109,"broken":false,"index":17},{"a":{"position":{"x":562,"y":453},"velocity":{"x":0,"y":0},"index":2,"highlight":[148,102,101]},"b":{"position":{"x":678,"y":453},"velocity":{"x":0,"y":0},"index":4,"highlight":[115,181,102]},"k":0.1,"restLength":116,"broken":false,"index":18},{"a":{"position":{"x":678,"y":453},"velocity":{"x":0,"y":0},"index":4,"highlight":[115,181,102]},"b":{"position":{"x":787,"y":453},"velocity":{"x":0,"y":0},"index":6,"highlight":[182,60,103]},"k":0.1,"restLength":109,"broken":false,"index":19},{"a":{"position":{"x":787,"y":453},"velocity":{"x":0,"y":0},"index":6,"highlight":[182,60,103]},"b":{"position":{"x":901,"y":451},"velocity":{"x":0,"y":0},"index":8,"highlight":[46,76,141]},"k":0.1,"restLength":114.0175425099138,"broken":false,"index":20},{"a":{"position":{"x":901,"y":451},"velocity":{"x":0,"y":0},"index":8,"highlight":[46,76,141]},"b":{"position":{"x":1015,"y":454},"velocity":{"x":0,"y":0},"index":10,"highlight":[125,139,108]},"k":0.1,"restLength":114.03946685248927,"broken":false,"index":21},{"a":{"position":{"x":1015,"y":454},"velocity":{"x":0,"y":0},"index":10,"highlight":[125,139,108]},"b":{"position":{"x":1132,"y":454},"velocity":{"x":0,"y":0},"index":12,"highlight":[244,194,4]},"k":0.1,"restLength":117,"broken":false,"index":22},{"a":{"position":{"x":453,"y":679},"velocity":{"x":0,"y":0},"index":16,"highlight":[230,117,173]},"b":{"position":{"x":678,"y":681},"velocity":{"x":0,"y":0},"index":17,"highlight":[225,233,6]},"k":0.1,"restLength":225.00888871331284,"broken":false,"index":23},{"a":{"position":{"x":678,"y":681},"velocity":{"x":0,"y":0},"index":17,"highlight":[225,233,6]},"b":{"position":{"x":904,"y":682},"velocity":{"x":0,"y":0},"index":18,"highlight":[227,18,155]},"k":0.1,"restLength":226.00221237855172,"broken":false,"index":24},{"a":{"position":{"x":904,"y":682},"velocity":{"x":0,"y":0},"index":18,"highlight":[227,18,155]},"b":{"position":{"x":1131,"y":679},"velocity":{"x":0,"y":0},"index":13,"highlight":[40,65,214]},"k":0.1,"restLength":227.01982292302142,"broken":false,"index":25},{"a":{"position":{"x":904,"y":682},"velocity":{"x":0,"y":0},"index":18,"highlight":[227,18,155]},"b":{"position":{"x":1015,"y":454},"velocity":{"x":0,"y":0},"index":10,"highlight":[125,139,108]},"k":0.1,"restLength":253.58430550804994,"broken":false,"index":26},{"a":{"position":{"x":1015,"y":454},"velocity":{"x":0,"y":0},"index":10,"highlight":[125,139,108]},"b":{"position":{"x":1131,"y":679},"velocity":{"x":0,"y":0},"index":13,"highlight":[40,65,214]},"k":0.1,"restLength":253.1422524984717,"broken":false,"index":27},{"a":{"position":{"x":904,"y":682},"velocity":{"x":0,"y":0},"index":18,"highlight":[227,18,155]},"b":{"position":{"x":787,"y":453},"velocity":{"x":0,"y":0},"index":6,"highlight":[182,60,103]},"k":0.1,"restLength":257.1575392633862,"broken":false,"index":28},{"a":{"position":{"x":787,"y":453},"velocity":{"x":0,"y":0},"index":6,"highlight":[182,60,103]},"b":{"position":{"x":678,"y":681},"velocity":{"x":0,"y":0},"index":17,"highlight":[225,233,6]},"k":0.1,"restLength":252.7152547829276,"broken":false,"index":29},{"a":{"position":{"x":678,"y":681},"velocity":{"x":0,"y":0},"index":17,"highlight":[225,233,6]},"b":{"position":{"x":562,"y":453},"velocity":{"x":0,"y":0},"index":2,"highlight":[148,102,101]},"k":0.1,"restLength":255.8124312851117,"broken":false,"index":30},{"a":{"position":{"x":562,"y":453},"velocity":{"x":0,"y":0},"index":2,"highlight":[148,102,101]},"b":{"position":{"x":453,"y":679},"velocity":{"x":0,"y":0},"index":16,"highlight":[230,117,173]},"k":0.1,"restLength":250.9123352886422,"broken":false,"index":31},{"a":{"position":{"x":678,"y":681},"velocity":{"x":0,"y":0},"index":17,"highlight":[225,233,6]},"b":{"position":{"x":679,"y":906},"velocity":{"x":0,"y":0},"index":15,"highlight":[226,86,82]},"k":0.1,"restLength":225.00222221124838,"broken":false,"index":32},{"a":{"position":{"x":904,"y":682},"velocity":{"x":0,"y":0},"index":18,"highlight":[227,18,155]},"b":{"position":{"x":904,"y":906},"velocity":{"x":0,"y":0},"index":14,"highlight":[52,157,14]},"k":0.1,"restLength":224,"broken":false,"index":33},{"a":{"position":{"x":904,"y":906},"velocity":{"x":0,"y":0},"index":14,"highlight":[52,157,14]},"b":{"position":{"x":678,"y":681},"velocity":{"x":0,"y":0},"index":17,"highlight":[225,233,6]},"k":0.1,"restLength":318.90594224629933,"broken":false,"index":34},{"a":{"position":{"x":904,"y":682},"velocity":{"x":0,"y":0},"index":18,"highlight":[227,18,155]},"b":{"position":{"x":679,"y":906},"velocity":{"x":0,"y":0},"index":15,"highlight":[226,86,82]},"k":0.1,"restLength":317.49173217581586,"broken":false,"index":35},{"a":{"position":{"x":904,"y":682},"velocity":{"x":0,"y":0},"index":18,"highlight":[227,18,155]},"b":{"position":{"x":901,"y":451},"velocity":{"x":0,"y":0},"index":8,"highlight":[46,76,141]},"k":0.1,"restLength":231.01947969814148,"broken":false,"index":36},{"a":{"position":{"x":678,"y":453},"velocity":{"x":0,"y":0},"index":4,"highlight":[115,181,102]},"b":{"position":{"x":678,"y":681},"velocity":{"x":0,"y":0},"index":17,"highlight":[225,233,6]},"k":0.1,"restLength":228,"broken":false,"index":37}],"masses":[{"position":{"x":453,"y":453},"velocity":{"x":0,"y":0},"index":0,"highlight":[20,23,172]},{"position":{"x":517,"y":229},"velocity":{"x":0,"y":0},"index":1,"highlight":[218,125,217]},{"position":{"x":562,"y":453},"velocity":{"x":0,"y":0},"index":2,"highlight":[148,102,101]},{"position":{"x":610,"y":228},"velocity":{"x":0,"y":0},"index":3,"highlight":[105,250,219]},{"position":{"x":678,"y":453},"velocity":{"x":0,"y":0},"index":4,"highlight":[115,181,102]},{"position":{"x":748,"y":229},"velocity":{"x":0,"y":0},"index":5,"highlight":[52,201,147]},{"position":{"x":787,"y":453},"velocity":{"x":0,"y":0},"index":6,"highlight":[182,60,103]},{"position":{"x":834,"y":231},"velocity":{"x":0,"y":0},"index":7,"highlight":[188,193,184]},{"position":{"x":901,"y":451},"velocity":{"x":0,"y":0},"index":8,"highlight":[46,76,141]},{"position":{"x":979,"y":229},"velocity":{"x":0,"y":0},"index":9,"highlight":[156,11,178]},{"position":{"x":1015,"y":454},"velocity":{"x":0,"y":0},"index":10,"highlight":[125,139,108]},{"position":{"x":1045,"y":228},"velocity":{"x":0,"y":0},"index":11,"highlight":[216,39,115]},{"position":{"x":1132,"y":454},"velocity":{"x":0,"y":0},"index":12,"highlight":[244,194,4]},{"position":{"x":1131,"y":679},"velocity":{"x":0,"y":0},"index":13,"highlight":[40,65,214]},{"position":{"x":904,"y":906},"velocity":{"x":0,"y":0},"index":14,"highlight":[52,157,14]},{"position":{"x":679,"y":906},"velocity":{"x":0,"y":0},"index":15,"highlight":[226,86,82]},{"position":{"x":453,"y":679},"velocity":{"x":0,"y":0},"index":16,"highlight":[230,117,173]},{"position":{"x":678,"y":681},"velocity":{"x":0,"y":0},"index":17,"highlight":[225,233,6]},{"position":{"x":904,"y":682},"velocity":{"x":0,"y":0},"index":18,"highlight":[227,18,155]}],"cursor":{"x":0,"y":0},"downMass":{"position":{"x":678,"y":453},"velocity":{"x":0,"y":0},"index":4,"highlight":[115,181,102]},"upMass":{"position":{"x":678,"y":681},"velocity":{"x":0,"y":0},"index":17,"highlight":[225,233,6]},"mode":0,"massRadius":9,"gravityOn":false,"editMode":false,"ground":1130.111111111111,"mouseCoords":{"x":2532,"y":57},"selectedSpring":{"a":{"position":{"x":904,"y":906},"velocity":{"x":0,"y":0},"index":14,"highlight":[52,157,14]},"b":{"position":{"x":678,"y":681},"velocity":{"x":0,"y":0},"index":17,"highlight":[225,233,6]},"k":0.1,"restLength":318.90594224629933,"broken":false,"index":34},"hard":["Tank","Rocket","Bridge","Tower"],"easy":["Building","Pyramid","Octagon"],"medium":["Boat"],"massPics":["pics/1.png","pics/2.png","pics/3.png"]}